pyutilib.virtualenv-4.7-py2.7-nspkg.pth
pyutilib/virtualenv/OrderedConfigParser.py
pyutilib/virtualenv/__init__.py
pyutilib/virtualenv/header.py
pyutilib/virtualenv/odict.py
pyutilib/virtualenv/vpy_create.py
pyutilib/virtualenv/vpy_install.py
pyutilib/virtualenv/wheels.py
pyutilib.virtualenv-4.7.dist-info/DESCRIPTION.rst
pyutilib.virtualenv-4.7.dist-info/METADATA
pyutilib.virtualenv-4.7.dist-info/RECORD
pyutilib.virtualenv-4.7.dist-info/WHEEL
pyutilib.virtualenv-4.7.dist-info/entry_points.txt
pyutilib.virtualenv-4.7.dist-info/metadata.json
pyutilib.virtualenv-4.7.dist-info/namespace_packages.txt
pyutilib.virtualenv-4.7.dist-info/top_level.txt
