Metadata-Version: 2.0
Name: pyutilib.virtualenv
Version: 4.7
Summary: PyUtilib utility for building custom virtualenv bootstrap scripts.
Home-page: https://software.sandia.gov/svn/public/pyutilib/pyutilib.virtualenv
Author: William E. Hart
Author-email: wehart@sandia.gov
License: BSD
Keywords: utility
Platform: any
Classifier: Development Status :: 4 - Beta
Classifier: Intended Audience :: End Users/Desktop
Classifier: License :: OSI Approved :: BSD License
Classifier: Natural Language :: English
Classifier: Operating System :: Microsoft :: Windows
Classifier: Operating System :: Unix
Classifier: Programming Language :: Python
Classifier: Programming Language :: Unix Shell
Classifier: Topic :: Scientific/Engineering :: Mathematics
Classifier: Topic :: Software Development :: Libraries :: Python Modules
Requires-Dist: virtualenv
